crazehub
